bafser/__init__.py
bafser/__main__.py
bafser/alembic.py
bafser/app.py
bafser/authentication.py
bafser/bafser_config.example.py
bafser/bafser_config.tgapi.py
bafser/cli.py
bafser/db_session.py
bafser/doc_api.py
bafser/jsonobj.py
bafser/logger.py
bafser/table_base.py
bafser/data/__init__.py
bafser/data/_roles.py
bafser/data/_tables.py
bafser/data/db_state.py
bafser/data/image.py
bafser/data/log.py
bafser/data/operation.py
bafser/data/permission.py
bafser/data/role.py
bafser/data/user.py
bafser/data/user_role.py
bafser/scripts/__init__.py
bafser/scripts/add_user.py
bafser/scripts/add_user_role.py
bafser/scripts/alembic.py
bafser/scripts/change_user_password.py
bafser/scripts/configure_webhook.py
bafser/scripts/init_project.py
bafser/scripts/remove_user_role.py
bafser/scripts/stickers.py
bafser/templates/docs.html
bafser/utils/__init__.py
bafser/utils/create_file_response.py
bafser/utils/create_folder_for_file.py
bafser/utils/get_all_vars.py
bafser/utils/get_datetime_now.py
bafser/utils/get_db_path.py
bafser/utils/get_db_session.py
bafser/utils/get_json.py
bafser/utils/get_json_values.py
bafser/utils/get_json_values_from_req.py
bafser/utils/get_secret_key.py
bafser/utils/get_userId.py
bafser/utils/import_all_tables.py
bafser/utils/ip_to_emoji.py
bafser/utils/jsonify_list.py
bafser/utils/listfind.py
bafser/utils/parse_date.py
bafser/utils/permission_required.py
bafser/utils/randstr.py
bafser/utils/register_blueprints.py
bafser/utils/response_msg.py
bafser/utils/response_not_found.py
bafser/utils/use_db_session.py
bafser/utils/use_user.py
bafser/utils/use_userId.py
bafser-2.5.2.dist-info/METADATA
bafser-2.5.2.dist-info/WHEEL
bafser-2.5.2.dist-info/entry_points.txt
bafser-2.5.2.dist-info/licenses/LICENSE
bafser-2.5.2.dist-info/RECORD
