Metadata-Version: 2.4
Name: bafser
Version: 2.5.2
Summary: Base for flask server
Project-URL: Homepage, https://github.com/MixelTe/bafser
Project-URL: Issues, https://github.com/MixelTe/bafser/issues
Author: Mixel Te
License-Expression: MIT
License-File: LICENSE
Classifier: Operating System :: OS Independent
Classifier: Programming Language :: Python :: 3.12
Requires-Python: >=3.12
Requires-Dist: alembic==1.16.4
Requires-Dist: flask-jwt-extended==4.7.1
Requires-Dist: flask==3.1.1
Requires-Dist: pymysql==1.1.1
Requires-Dist: sqlalchemy-serializer==1.4.22
Requires-Dist: sqlalchemy==2.0.29
Requires-Dist: werkzeug==3.1.3
